PyFastNER/CFastCNER.pyx
PyFastNER/FastCNER.py
PyFastNER/FastNER.py
PyFastNER/IOUtils.py
PyFastNER/ReplicationFunctionsLambda.py
PyFastNER/WildCardFunctions.py
PyFastNER/__init__.py
PyFastNER-1.0.10.data/data/demo_data/crule_test.tsv
PyFastNER-1.0.10.dist-info/LICENSE
PyFastNER-1.0.10.dist-info/METADATA
PyFastNER-1.0.10.dist-info/WHEEL
PyFastNER-1.0.10.dist-info/top_level.txt
PyFastNER-1.0.10.dist-info/RECORD
