Metadata-Version: 1.1
Name: PyFastNER
Version: 1.0.10
Summary: A fast implementation of dictionary based named entity recognition.
Home-page: https://github.com/jianlins/PyFastNER
Author: Jianlin
Author-email: jianlinshi.cn@gmail.com
License: Apache License
Keywords: PyFastNER,ner,regex
Platform: UNKNOWN
Classifier: Programming Language :: Python :: 3
Classifier: Programming Language :: Python :: 3.6
Classifier: Programming Language :: Python :: 3.7
Classifier: Programming Language :: Python :: 3.8
Classifier: Development Status :: 3 - Alpha
Classifier: Intended Audience :: Developers
Classifier: License :: OSI Approved :: Apache Software License
Classifier: Operating System :: OS Independent
Classifier: Topic :: Software Development :: Libraries :: Python Modules
Classifier: Topic :: Text Processing :: Linguistic
